hljm/__init__.py
hljm/hljm.py
hljm-2.0.0.dist-info/METADATA
hljm-2.0.0.dist-info/WHEEL
hljm-2.0.0.dist-info/top_level.txt
hljm-2.0.0.dist-info/RECORD
