Metadata-Version: 2.1
Name: hljm
Version: 2.0.0
Summary: Description of your library
Home-page: UNKNOWN
Author: 黑龙
Author-email: 2076293320@qq.com
License: UNKNOWN
Platform: UNKNOWN
